cyclonepackagedemo/__init__.py
cyclonepackagedemo-0.1.0.dist-info/METADATA
cyclonepackagedemo-0.1.0.dist-info/WHEEL
cyclonepackagedemo-0.1.0.dist-info/entry_points.txt
cyclonepackagedemo-0.1.0.dist-info/RECORD
